Workbook

Sheet Contas
A1: ID_Conta | B1: Nome_Conta | C1: Tipo | D1: Banco | E1: Saldo_Inicial | F1: Ativa
A2: CTA01 | B2: Nubank Conta | C2: Corrente | D2: Nubank | E2: 1500 | F2: Sim
A3: CTA02 | B3: Nubank Cartao | C3: Cartao | D3: Nubank | E3: 0 | F3: Sim
A4: CTA03 | B4: Banco do Brasil | C4: Corrente | D4: Banco do Brasil | E4: 3200 | F4: Sim
A5: CTA04 | B5: Itau Conta | C5: Corrente | D5: Itau | E5: 800 | F5: Sim
A6: CTA05 | B6: Itau Cartao | C6: Cartao | D6: Itau | E6: 0 | F6: Sim
A7: CTA06 | B7: Carteira | C7: Dinheiro | D7: - | E7: 150 | F7: Sim
A8: CTA07 | B8: Investimentos | C8: Investimento | D8: - | E8: 5000 | F8: Sim
A10: Legenda: preencha/edite estas linhas conforme suas contas reais. Tipo aceita: Corrente, Cartao, Dinheiro, Investimento.

Sheet Categorias
A1: ID_Categoria | B1: Nome_Categoria | C1: Tipo | D1: Grupo
A2: CAT01 | B2: Salario | C2: Receita | D2: Salario
A3: CAT02 | B3: Freelance / Extra | C3: Receita | D3: Salario
A4: CAT03 | B4: Rendimentos de Investimentos | C4: Receita | D4: Renda Variavel
A5: CAT04 | B5: Outras Receitas | C5: Receita | D5: Outros
A6: CAT05 | B6: Aluguel / Financiamento | C6: Despesa | D6: Moradia
A7: CAT06 | B7: Condominio | C7: Despesa | D7: Moradia
A8: CAT07 | B8: Energia Eletrica | C8: Despesa | D8: Moradia
A9: CAT08 | B9: Agua | C9: Despesa | D9: Moradia
A10: CAT09 | B10: Internet / Telefone | C10: Despesa | D10: Moradia
A11: CAT10 | B11: Supermercado | C11: Despesa | D11: Alimentacao
A12: CAT11 | B12: Restaurantes / Delivery | C12: Despesa | D12: Alimentacao
... A31: CAT30 | B31: Reserva de Emergencia | C31: Investimento | D31: Renda Fixa
A33: Legenda: adicione/edite categorias livremente. Tipo deve ser Receita, Despesa ou Investimento (usado pelas formulas do Resumo_Mensal).

Sheet Lancamentos
A1: ID_Lancamento | B1: Data | C1: Tipo | D1: Conta | E1: Categoria | F1: Descricao | G1: Valor | H1: Forma_Pagamento | I1: Parcela_Atual | J1: Total_Parcelas | K1: Recorrente | L1: Observacoes | M1: Mes_Referencia
A2: LC0001 | B2: 46239 | C2: Receita | D2: Banco do Brasil | E2: Salario | F2: Salario mensal | G2: 6500 | H2: Transferencia | I2: 1 | J2: 1 | K2: Sim | M2: =IF(B2="","",TEXT(B2,"AAAA-MM"))
A3: LC0002 | B3: 46240 | C3: Despesa | D3: Nubank Cartao | E3: Supermercado | F3: Compra do mes | G3: 780.5 | H3: Credito | I3: 1 | J3: 1 | K3: Nao | M3: =IF(B3="","",TEXT(B3,"AAAA-MM"))
A4: LC0003 | B4: 46244 | C4: Despesa | D4: Itau Conta | E4: Aluguel / Financiamento | F4: Aluguel | G4: 2100 | H4: Transferencia | I4: 1 | J4: 1 | K4: Sim | M4: =IF(B4="","",TEXT(B4,"AAAA-MM"))
A5: LC0004 | B5: 46249 | C5: Investimento | D5: Investimentos | E5: Renda Fixa (CDB, Tesouro) | F5: Aporte Tesouro Selic | G5: 500 | H5: Transferencia | I5: 1 | J5: 1 | K5: Sim | M5: =IF(B5="","",TEXT(B5,"AAAA-MM"))
A6: LC0005 | B6: 46267 | C6: Despesa | D6: Carteira | E6: Transporte por App / Publico | F6: Taxi | G6: 35 | H6: Dinheiro | I6: 1 | J6: 1 | K6: Nao | M6: =IF(B6="","",TEXT(B6,"AAAA-MM"))
M7: =IF(B7="","",TEXT(B7,"AAAA-MM"))
M8: =IF(B8="","",TEXT(B8,"AAAA-MM"))
M9: =IF(B9="","",TEXT(B9,"AAAA-MM"))
M10: =IF(B10="","",TEXT(B10,"AAAA-MM"))
M11: =IF(B11="","",TEXT(B11,"AAAA-MM"))
M12: =IF(B12="","",TEXT(B12,"AAAA-MM"))
M13: =IF(B13="","",TEXT(B13,"AAAA-MM"))
M14: =IF(B14="","",TEXT(B14,"AAAA-MM"))
M15: =IF(B15="","",TEXT(B15,"AAAA-MM"))
M16: =IF(B16="","",TEXT(B16,"AAAA-MM"))
M17: =IF(B17="","",TEXT(B17,"AAAA-MM"))
M18: =IF(B18="","",TEXT(B18,"AAAA-MM"))
... M36: =IF(B36="","",TEXT(B36,"AAAA-MM"))
A39: Legenda: esta e a tabela principal, alimentada pelo formulario do AppSheet (uma linha por lancamento). Mes_Referencia e calculada automaticamente a partir da Data - nao editar manualmente. Linhas de exemplo (LC0001-LC0005) sao ficticias, pode apagar.

Sheet Resumo_Mensal
A1: Mes | B1: Total_Receitas | C1: Total_Despesas | D1: Total_Investimentos | E1: Saldo_do_Mes | F1: Taxa_de_Poupanca | G1: Saldo_Acumulado | I1: Gastos por Categoria - Mes mais recente
A2: 2025-10 | B2: =SUMIFS(Lancamentos!$G:$G,Lancamentos!$C:$C,"Receita",Lancamentos!$M:$M,A2) | C2: =SUMIFS(Lancamentos!$G:$G,Lancamentos!$C:$C,"Despesa",Lancamentos!$M:$M,A2) | D2: =SUMIFS(Lancamentos!$G:$G,Lancamentos!$C:$C,"Investimento",Lancamentos!$M:$M,A2) | E2: =B2-C2-D2 | F2: =IFERROR(E2/B2,0) | G2: =E2 | I2: Categoria | J2: Total_Gasto
A3: 2025-11 | B3: =SUMIFS(Lancamentos!$G:$G,Lancamentos!$C:$C,"Receita",Lancamentos!$M:$M,A3) | C3: =SUMIFS(Lancamentos!$G:$G,Lancamentos!$C:$C,"Despesa",Lancamentos!$M:$M,A3) | D3: =SUMIFS(Lancamentos!$G:$G,Lancamentos!$C:$C,"Investimento",Lancamentos!$M:$M,A3) | E3: =B3-C3-D3 | F3: =IFERROR(E3/B3,0) | G3: =G2+E3 | I3: Aluguel / Financiamento | J3: =SUMIFS(Lancamentos!$G:$G,Lancamentos!$E:$E,I3,Lancamentos!$M:$M,$A$13)
A4: 2025-12 | B4: =SUMIFS(Lancamentos!$G:$G,Lancamentos!$C:$C,"Receita",Lancamentos!$M:$M,A4) | C4: =SUMIFS(Lancamentos!$G:$G,Lancamentos!$C:$C,"Despesa",Lancamentos!$M:$M,A4) | D4: =SUMIFS(Lancamentos!$G:$G,Lancamentos!$C:$C,"Investimento",Lancamentos!$M:$M,A4) | E4: =B4-C4-D4 | F4: =IFERROR(E4/B4,0) | G4: =G3+E4 | I4: Condominio | J4: =SUMIFS(Lancamentos!$G:$G,Lancamentos!$E:$E,I4,Lancamentos!$M:$M,$A$13)
A5: 2026-01 | B5: =SUMIFS(Lancamentos!$G:$G,Lancamentos!$C:$C,"Receita",Lancamentos!$M:$M,A5) | C5: =SUMIFS(Lancamentos!$G:$G,Lancamentos!$C:$C,"Despesa",Lancamentos!$M:$M,A5) | D5: =SUMIFS(Lancamentos!$G:$G,Lancamentos!$C:$C,"Investimento",Lancamentos!$M:$M,A5) | E5: =B5-C5-D5 | F5: =IFERROR(E5/B5,0) | G5: =G4+E5 | I5: Energia Eletrica | J5: =SUMIFS(Lancamentos!$G:$G,Lancamentos!$E:$E,I5,Lancamentos!$M:$M,$A$13)
A6: 2026-02 | B6: =SUMIFS(Lancamentos!$G:$G,Lancamentos!$C:$C,"Receita",Lancamentos!$M:$M,A6) | C6: =SUMIFS(Lancamentos!$G:$G,Lancamentos!$C:$C,"Despesa",Lancamentos!$M:$M,A6) | D6: =SUMIFS(Lancamentos!$G:$G,Lancamentos!$C:$C,"Investimento",Lancamentos!$M:$M,A6) | E6: =B6-C6-D6 | F6: =IFERROR(E6/B6,0) | G6: =G5+E6 | I6: Agua | J6: =SUMIFS(Lancamentos!$G:$G,Lancamentos!$E:$E,I6,Lancamentos!$M:$M,$A$13)
A7: 2026-03 | B7: =SUMIFS(Lancamentos!$G:$G,Lancamentos!$C:$C,"Receita",Lancamentos!$M:$M,A7) | C7: =SUMIFS(Lancamentos!$G:$G,Lancamentos!$C:$C,"Despesa",Lancamentos!$M:$M,A7) | D7: =SUMIFS(Lancamentos!$G:$G,Lancamentos!$C:$C,"Investimento",Lancamentos!$M:$M,A7) | E7: =B7-C7-D7 | F7: =IFERROR(E7/B7,0) | G7: =G6+E7 | I7: Internet / Telefone | J7: =SUMIFS(Lancamentos!$G:$G,Lancamentos!$E:$E,I7,Lancamentos!$M:$M,$A$13)
A8: 2026-04 | B8: =SUMIFS(Lancamentos!$G:$G,Lancamentos!$C:$C,"Receita",Lancamentos!$M:$M,A8) | C8: =SUMIFS(Lancamentos!$G:$G,Lancamentos!$C:$C,"Despesa",Lancamentos!$M:$M,A8) | D8: =SUMIFS(Lancamentos!$G:$G,Lancamentos!$C:$C,"Investimento",Lancamentos!$M:$M,A8) | E8: =B8-C8-D8 | F8: =IFERROR(E8/B8,0) | G8: =G7+E8 | I8: Supermercado | J8: =SUMIFS(Lancamentos!$G:$G,Lancamentos!$E:$E,I8,Lancamentos!$M:$M,$A$13)
A9: 2026-05 | B9: =SUMIFS(Lancamentos!$G:$G,Lancamentos!$C:$C,"Receita",Lancamentos!$M:$M,A9) | C9: =SUMIFS(Lancamentos!$G:$G,Lancamentos!$C:$C,"Despesa",Lancamentos!$M:$M,A9) | D9: =SUMIFS(Lancamentos!$G:$G,Lancamentos!$C:$C,"Investimento",Lancamentos!$M:$M,A9) | E9: =B9-C9-D9 | F9: =IFERROR(E9/B9,0) | G9: =G8+E9 | I9: Restaurantes / Delivery | J9: =SUMIFS(Lancamentos!$G:$G,Lancamentos!$E:$E,I9,Lancamentos!$M:$M,$A$13)
A10: 2026-06 | B10: =SUMIFS(Lancamentos!$G:$G,Lancamentos!$C:$C,"Receita",Lancamentos!$M:$M,A10) | C10: =SUMIFS(Lancamentos!$G:$G,Lancamentos!$C:$C,"Despesa",Lancamentos!$M:$M,A10) | D10: =SUMIFS(Lancamentos!$G:$G,Lancamentos!$C:$C,"Investimento",Lancamentos!$M:$M,A10) | E10: =B10-C10-D10 | F10: =IFERROR(E10/B10,0) | G10: =G9+E10 | I10: Combustivel | J10: =SUMIFS(Lancamentos!$G:$G,Lancamentos!$E:$E,I10,Lancamentos!$M:$M,$A$13)
A11: 2026-07 | B11: =SUMIFS(Lancamentos!$G:$G,Lancamentos!$C:$C,"Receita",Lancamentos!$M:$M,A11) | C11: =SUMIFS(Lancamentos!$G:$G,Lancamentos!$C:$C,"Despesa",Lancamentos!$M:$M,A11) | D11: =SUMIFS(Lancamentos!$G:$G,Lancamentos!$C:$C,"Investimento",Lancamentos!$M:$M,A11) | E11: =B11-C11-D11 | F11: =IFERROR(E11/B11,0) | G11: =G10+E11 | I11: Transporte por App / Publico | J11: =SUMIFS(Lancamentos!$G:$G,Lancamentos!$E:$E,I11,Lancamentos!$M:$M,$A$13)
A12: 2026-08 | B12: =SUMIFS(Lancamentos!$G:$G,Lancamentos!$C:$C,"Receita",Lancamentos!$M:$M,A12) | C12: =SUMIFS(Lancamentos!$G:$G,Lancamentos!$C:$C,"Despesa",Lancamentos!$M:$M,A12) | D12: =SUMIFS(Lancamentos!$G:$G,Lancamentos!$C:$C,"Investimento",Lancamentos!$M:$M,A12) | E12: =B12-C12-D12 | F12: =IFERROR(E12/B12,0) | G12: =G11+E12 | I12: Manutencao Veiculo | J12: =SUMIFS(Lancamentos!$G:$G,Lancamentos!$E:$E,I12,Lancamentos!$M:$M,$A$13)
A13: 2026-09 | B13: =SUMIFS(Lancamentos!$G:$G,Lancamentos!$C:$C,"Receita",Lancamentos!$M:$M,A13) | C13: =SUMIFS(Lancamentos!$G:$G,Lancamentos!$C:$C,"Despesa",Lancamentos!$M:$M,A13) | D13: =SUMIFS(Lancamentos!$G:$G,Lancamentos!$C:$C,"Investimento",Lancamentos!$M:$M,A13) | E13: =B13-C13-D13 | F13: =IFERROR(E13/B13,0) | G13: =G12+E13 | I13: Plano de Saude | J13: =SUMIFS(Lancamentos!$G:$G,Lancamentos!$E:$E,I13,Lancamentos!$M:$M,$A$13)
I14: Farmacia | J14: =SUMIFS(Lancamentos!$G:$G,Lancamentos!$E:$E,I14,Lancamentos!$M:$M,$A$13)
A15: Legenda: esta aba e 100% calculada a partir da aba Lancamentos - nao editar as formulas. 'Mes' esta no formato AAAA-MM e cobre os ultimos 12 meses. A tabela 'Gastos por Categoria' sempre mostra o mes mais recente da lista ao lado. | I15: Consultas / Exames | J15: =SUMIFS(Lancamentos!$G:$G,Lancamentos!$E:$E,I15,Lancamentos!$M:$M,$A$13)
I16: Cinema / Lazer | J16: =SUMIFS(Lancamentos!$G:$G,Lancamentos!$E:$E,I16,Lancamentos!$M:$M,$A$13)
I17: Viagens | J17: =SUMIFS(Lancamentos!$G:$G,Lancamentos!$E:$E,I17,Lancamentos!$M:$M,$A$13)
I18: Cursos / Livros | J18: =SUMIFS(Lancamentos!$G:$G,Lancamentos!$E:$E,I18,Lancamentos!$M:$M,$A$13)
I19: Mensalidade Escolar | J19: =SUMIFS(Lancamentos!$G:$G,Lancamentos!$E:$E,I19,Lancamentos!$M:$M,$A$13)
I20: Streaming / Assinaturas | J20: =SUMIFS(Lancamentos!$G:$G,Lancamentos!$E:$E,I20,Lancamentos!$M:$M,$A$13)
I21: Vestuario | J21: =SUMIFS(Lancamentos!$G:$G,Lancamentos!$E:$E,I21,Lancamentos!$M:$M,$A$13)
I22: Cuidados Pessoais | J22: =SUMIFS(Lancamentos!$G:$G,Lancamentos!$E:$E,I22,Lancamentos!$M:$M,$A$13)
I23: Impostos / Taxas | J23: =SUMIFS(Lancamentos!$G:$G,Lancamentos!$E:$E,I23,Lancamentos!$M:$M,$A$13)
I24: Pets | J24: =SUMIFS(Lancamentos!$G:$G,Lancamentos!$E:$E,I24,Lancamentos!$M:$M,$A$13)
I25: Presentes / Doacoes | J25: =SUMIFS(Lancamentos!$G:$G,Lancamentos!$E:$E,I25,Lancamentos!$M:$M,$A$13)

Sheet Orcamento
A1: Categoria | B1: Valor_Orcado | C1: Valor_Gasto | D1: Diferenca | E1: Status
A2: Aluguel / Financiamento | B2: 0 | C2: =SUMIFS(Lancamentos!$G:$G,Lancamentos!$E:$E,A2,Lancamentos!$M:$M,TEXT(TODAY(),"AAAA-MM")) | D2: =B2-C2 | E2: =IF(B2=0,"Sem orcamento",IF(C2<=B2,"Dentro do orcado","Estourado"))
A3: Condominio | B3: 0 | C3: =SUMIFS(Lancamentos!$G:$G,Lancamentos!$E:$E,A3,Lancamentos!$M:$M,TEXT(TODAY(),"AAAA-MM")) | D3: =B3-C3 | E3: =IF(B3=0,"Sem orcamento",IF(C3<=B3,"Dentro do orcado","Estourado"))
A4: Energia Eletrica | B4: 0 | C4: =SUMIFS(Lancamentos!$G:$G,Lancamentos!$E:$E,A4,Lancamentos!$M:$M,TEXT(TODAY(),"AAAA-MM")) | D4: =B4-C4 | E4: =IF(B4=0,"Sem orcamento",IF(C4<=B4,"Dentro do orcado","Estourado"))
A5: Agua | B5: 0 | C5: =SUMIFS(Lancamentos!$G:$G,Lancamentos!$E:$E,A5,Lancamentos!$M:$M,TEXT(TODAY(),"AAAA-MM")) | D5: =B5-C5 | E5: =IF(B5=0,"Sem orcamento",IF(C5<=B5,"Dentro do orcado","Estourado"))
A6: Internet / Telefone | B6: 0 | C6: =SUMIFS(Lancamentos!$G:$G,Lancamentos!$E:$E,A6,Lancamentos!$M:$M,TEXT(TODAY(),"AAAA-MM")) | D6: =B6-C6 | E6: =IF(B6=0,"Sem orcamento",IF(C6<=B6,"Dentro do orcado","Estourado"))
A7: Supermercado | B7: 0 | C7: =SUMIFS(Lancamentos!$G:$G,Lancamentos!$E:$E,A7,Lancamentos!$M:$M,TEXT(TODAY(),"AAAA-MM")) | D7: =B7-C7 | E7: =IF(B7=0,"Sem orcamento",IF(C7<=B7,"Dentro do orcado","Estourado"))
A8: Restaurantes / Delivery | B8: 0 | C8: =SUMIFS(Lancamentos!$G:$G,Lancamentos!$E:$E,A8,Lancamentos!$M:$M,TEXT(TODAY(),"AAAA-MM")) | D8: =B8-C8 | E8: =IF(B8=0,"Sem orcamento",IF(C8<=B8,"Dentro do orcado","Estourado"))
A9: Combustivel | B9: 0 | C9: =SUMIFS(Lancamentos!$G:$G,Lancamentos!$E:$E,A9,Lancamentos!$M:$M,TEXT(TODAY(),"AAAA-MM")) | D9: =B9-C9 | E9: =IF(B9=0,"Sem orcamento",IF(C9<=B9,"Dentro do orcado","Estourado"))
A10: Transporte por App / Publico | B10: 0 | C10: =SUMIFS(Lancamentos!$G:$G,Lancamentos!$E:$E,A10,Lancamentos!$M:$M,TEXT(TODAY(),"AAAA-MM")) | D10: =B10-C10 | E10: =IF(B10=0,"Sem orcamento",IF(C10<=B10,"Dentro do orcado","Estourado"))
A11: Manutencao Veiculo | B11: 0 | C11: =SUMIFS(Lancamentos!$G:$G,Lancamentos!$E:$E,A11,Lancamentos!$M:$M,TEXT(TODAY(),"AAAA-MM")) | D11: =B11-C11 | E11: =IF(B11=0,"Sem orcamento",IF(C11<=B11,"Dentro do orcado","Estourado"))
A12: Plano de Saude | B12: 0 | C12: =SUMIFS(Lancamentos!$G:$G,Lancamentos!$E:$E,A12,Lancamentos!$M:$M,TEXT(TODAY(),"AAAA-MM")) | D12: =B12-C12 | E12: =IF(B12=0,"Sem orcamento",IF(C12<=B12,"Dentro do orcado","Estourado"))
A13: Farmacia | B13: 0 | C13: =SUMIFS(Lancamentos!$G:$G,Lancamentos!$E:$E,A13,Lancamentos!$M:$M,TEXT(TODAY(),"AAAA-MM")) | D13: =B13-C13 | E13: =IF(B13=0,"Sem orcamento",IF(C13<=B13,"Dentro do orcado","Estourado"))
... A24: Presentes / Doacoes | B24: 0 | C24: =SUMIFS(Lancamentos!$G:$G,Lancamentos!$E:$E,A24,Lancamentos!$M:$M,TEXT(TODAY(),"AAAA-MM")) | D24: =B24-C24 | E24: =IF(B24=0,"Sem orcamento",IF(C24<=B24,"Dentro do orcado","Estourado"))
A26: Legenda (celulas azuis = editaveis): preencha 'Valor_Orcado' com o limite mensal desejado para cada categoria. 'Valor_Gasto' e calculado automaticamente com base no mes atual (hoje).
